MANIFEST.in
README.md
package.json
setup.py
alert/build.gradle
alert/gradle.properties
alert/gradlew
alert/gradlew.bat
alert/settings.gradle
alert/.idea/.name
alert/.idea/compiler.xml
alert/.idea/gradle.xml
alert/.idea/misc.xml
alert/app/build.gradle
alert/app/proguard-rules.pro
alert/app/src/androidTest/java/com/example/myapplication/ExampleInstrumentedTest.kt
alert/app/src/main/AndroidManifest.xml
alert/app/src/main/java/com/example/myapplication/MainActivity.kt
alert/app/src/main/res/drawable/ic_baseline_warning_24.xml
alert/app/src/main/res/drawable/ic_launcher_background.xml
alert/app/src/main/res/drawable-v24/ic_launcher_foreground.xml
alert/app/src/main/res/layout/activity_main.xml
alert/app/src/main/res/mipmap-anydpi-v26/ic_launcher.xml
alert/app/src/main/res/mipmap-anydpi-v26/ic_launcher_round.xml
alert/app/src/main/res/mipmap-hdpi/ic_launcher.webp
alert/app/src/main/res/mipmap-hdpi/ic_launcher_round.webp
alert/app/src/main/res/mipmap-mdpi/ic_launcher.webp
alert/app/src/main/res/mipmap-mdpi/ic_launcher_round.webp
alert/app/src/main/res/mipmap-xhdpi/ic_launcher.webp
alert/app/src/main/res/mipmap-xhdpi/ic_launcher_round.webp
alert/app/src/main/res/mipmap-xxhdpi/ic_launcher.webp
alert/app/src/main/res/mipmap-xxhdpi/ic_launcher_round.webp
alert/app/src/main/res/mipmap-xxxhdpi/ic_launcher.webp
alert/app/src/main/res/mipmap-xxxhdpi/ic_launcher_round.webp
alert/app/src/main/res/values/colors.xml
alert/app/src/main/res/values/strings.xml
alert/app/src/main/res/values/themes.xml
alert/app/src/main/res/values-night/themes.xml
alert/app/src/main/res/xml/backup_rules.xml
alert/app/src/main/res/xml/data_extraction_rules.xml
alert/app/src/test/java/com/example/myapplication/ExampleUnitTest.kt
alert/gradle/wrapper/gradle-wrapper.jar
alert/gradle/wrapper/gradle-wrapper.properties
animation/build.gradle
animation/gradle.properties
animation/gradlew
animation/gradlew.bat
animation/settings.gradle
animation/.idea/compiler.xml
animation/.idea/gradle.xml
madlabjs.egg-info/PKG-INFO
madlabjs.egg-info/SOURCES.txt
madlabjs.egg-info/dependency_links.txt
madlabjs.egg-info/not-zip-safe
madlabjs.egg-info/top_level.txt
