Metadata-Version: 2.1
Name: madlabjs
Version: 2.0.0
Summary: Android project files package with preserved folder structure
Author: Your Name
Author-email: your.email@example.com
